deepset.py
deepset-1.1.0.dist-info/licenses/LICENSE
deepset-1.1.0.dist-info/METADATA
deepset-1.1.0.dist-info/WHEEL
deepset-1.1.0.dist-info/top_level.txt
deepset-1.1.0.dist-info/RECORD
