Metadata-Version: 2.4
Name: deepset
Version: 1.1.0
Summary: Recursive subset comparison for complex nested Python data structures
Author-email: Perry Kundert <perry@dominionrnd.com>
License-Expression: MIT
Project-URL: Homepage, https://github.com/pjkundert/python-deepset
Project-URL: Bug Reports, https://github.com/pjkundert/python-deepset/issues
Project-URL: Source, https://github.com/pjkundert/python-deepset
Keywords: comparison,subset,recursive,nested,data-structures
Classifier: Development Status :: 4 - Beta
Classifier: Intended Audience :: Developers
Classifier: Programming Language :: Python :: 3
Classifier: Programming Language :: Python :: 3.6
Classifier: Programming Language :: Python :: 3.7
Classifier: Programming Language :: Python :: 3.8
Classifier: Programming Language :: Python :: 3.9
Classifier: Programming Language :: Python :: 3.10
Classifier: Programming Language :: Python :: 3.11
Classifier: Programming Language :: Python :: 3.12
Classifier: Programming Language :: Python :: 3.13
Classifier: Topic :: Software Development :: Libraries :: Python Modules
Classifier: Topic :: Utilities
Requires-Python: >=3.6
License-File: LICENSE
Provides-Extra: dev
Requires-Dist: build; extra == "dev"
Requires-Dist: setuptools; extra == "dev"
Requires-Dist: wheel; extra == "dev"
Requires-Dist: pytest>=6.0; extra == "dev"
Requires-Dist: black>=20.0; extra == "dev"
Requires-Dist: flake8; extra == "dev"
Requires-Dist: isort>=5.0; extra == "dev"
Requires-Dist: autopep8; extra == "dev"
Dynamic: license-file
